LICENSE
README.md
setup.cfg
setup.py
netbox_subnet_allocator/__init__.py
netbox_subnet_allocator/models.py
netbox_subnet_allocator.egg-info/PKG-INFO
netbox_subnet_allocator.egg-info/SOURCES.txt
netbox_subnet_allocator.egg-info/dependency_links.txt
netbox_subnet_allocator.egg-info/not-zip-safe
netbox_subnet_allocator.egg-info/top_level.txt