Metadata-Version: 2.1
Name: netbox-subnet-allocator
Version: 0.2
Summary: A NetBox plugin for managing the allocation of subnets
Home-page: UNKNOWN
License: UNKNOWN
Platform: UNKNOWN
License-File: LICENSE
